at2/__init__.py
at2/utils.py
at2/attribution/__init__.py
at2/attribution/attention.py
at2/attribution/attributors.py
at2/attribution/features.py
at2/attribution/score_estimators.py
at2/attribution/trainer.py
at2/attribution/utils.py
at2/tasks/__init__.py
at2/tasks/base.py
at2/tasks/chat.py
at2/tasks/context_attribution.py
at2/tasks/thought_attribution.py
at2-0.0.1.dist-info/licenses/LICENSE
at2-0.0.1.dist-info/METADATA
at2-0.0.1.dist-info/WHEEL
at2-0.0.1.dist-info/top_level.txt
at2-0.0.1.dist-info/RECORD
