Metadata-Version: 2.4
Name: at2
Version: 0.0.1
Summary: Attribute statements generated by LLMs to preceding tokens using attention weights.
Author-email: Benjamin Cohen-Wang <bencw@mit.edu>
Project-URL: Homepage, https://github.com/MadryLab/AT2
Project-URL: Issues, https://github.com/MadryLab/AT2/issues
Classifier: Programming Language :: Python :: 3
Classifier: License :: OSI Approved :: MIT License
Classifier: Operating System :: OS Independent
Requires-Python: >=3.10
License-File: LICENSE
Requires-Dist: numpy
Requires-Dist: torch
Requires-Dist: pandas
Requires-Dist: nltk>=3.8.2
Requires-Dist: spacy
Requires-Dist: scikit-learn
Requires-Dist: matplotlib
Requires-Dist: tqdm
Requires-Dist: ipywidgets
Requires-Dist: transformers
Requires-Dist: datasets
Requires-Dist: huggingface-hub
Provides-Extra: optional
Requires-Dist: flash-attn; extra == "optional"
Requires-Dist: accelerate; extra == "optional"
Provides-Extra: test
Requires-Dist: pytest; extra == "test"
Dynamic: license-file
